pyxmahjongg/__init__.py
pyxmahjongg/pyxmahjongg.py
pyxmahjongg/images/.DS_Store
pyxmahjongg/images/dorothys.png
pyxmahjongg/layouts/arena
pyxmahjongg/layouts/arrow
pyxmahjongg/layouts/boar
pyxmahjongg/layouts/bridge
pyxmahjongg/layouts/ceremonial
pyxmahjongg/layouts/deepwell
pyxmahjongg/layouts/default
pyxmahjongg/layouts/dog
pyxmahjongg/layouts/dragon
pyxmahjongg/layouts/farandole
pyxmahjongg/layouts/hare
pyxmahjongg/layouts/horse
pyxmahjongg/layouts/hourglass
pyxmahjongg/layouts/monkey
pyxmahjongg/layouts/ox
pyxmahjongg/layouts/papillon
pyxmahjongg/layouts/ram
pyxmahjongg/layouts/rat
pyxmahjongg/layouts/rooster
pyxmahjongg/layouts/schoon
pyxmahjongg/layouts/snake
pyxmahjongg/layouts/test
pyxmahjongg/layouts/theater
pyxmahjongg/layouts/tiger
pyxmahjongg/layouts/wedges
pyxmahjongg-0.2.5.dist-info/DESCRIPTION.rst
pyxmahjongg-0.2.5.dist-info/METADATA
pyxmahjongg-0.2.5.dist-info/RECORD
pyxmahjongg-0.2.5.dist-info/WHEEL
pyxmahjongg-0.2.5.dist-info/entry_points.txt
pyxmahjongg-0.2.5.dist-info/metadata.json
pyxmahjongg-0.2.5.dist-info/top_level.txt
