Metadata-Version: 2.0
Name: pyxmahjongg
Version: 0.2.5
Summary: The classic UNIX xmahjongg for Python 3
Home-page: https://github.com/kbr/pyxmahjongg
Author: Klaus Bremer
Author-email: bremer@bremer-media.de
License: Free for non-commercial use
Keywords: mahjongg game
Platform: UNKNOWN
Classifier: Development Status :: 4 - Beta
Classifier: Environment :: Console
Classifier: Intended Audience :: Other Audience
Classifier: License :: Free for non-commercial use
Classifier: Natural Language :: English
Classifier: Programming Language :: Python
Classifier: Programming Language :: Python :: 3
Classifier: Programming Language :: Python :: 3.6
Requires-Dist: pillow (>=4.0.0)
